melo/__init__.py
melo/dist.py
melo/melo.py
melo/nfl.dat
melo-1.1.0.dist-info/LICENSE
melo-1.1.0.dist-info/METADATA
melo-1.1.0.dist-info/WHEEL
melo-1.1.0.dist-info/top_level.txt
melo-1.1.0.dist-info/RECORD
